{"local_language_id":{"1":6,"2":6,"3":6,"4":6,"5":6,"6":6,"7":6,"8":6,"9":6,"10":6,"11":6,"12":6,"13":6,"14":6,"15":6,"16":6,"17":6,"18":6,"19":6,"20":6,"1__1":9,"2__1":9,"3__1":9,"4__1":9,"5__1":9,"6__1":9,"7__1":9,"8__1":9,"9__1":9,"10__1":9,"11__1":9,"12__1":9,"13__1":9,"14__1":9,"15__1":9,"16__1":9,"17__1":9,"18__1":9,"19__1":9,"20__1":9,"4__2":10,"11__2":10,"5__2":10,"10__2":10,"3__2":10,"6__2":10,"8__2":10,"2__2":10,"9__2":10,"7__2":10,"1__2":10,"13__2":10},"name":{"1":"Kontakt","2":"Hat eine Aufladerunde","3":"Muss aufladen","4":"Blockiert von Scanner and Schutzschild","5":"Reflektierbar","6":"Übernehmbar","7":"Kopierbar von Spiegeltrick","8":"Hieb basierend","9":"Sound basierend","10":"Nicht nutzbar bei hoher Erdanziehung","11":"Enteist bei benutzung","12":"Trifft gegenüber liegende Seite in 3er Kämpfen","13":"Heilt","14":"Ignoriert Delegator","15":"Pulver basierend","16":"Kiefer basierend","17":"Megawumme basierend","18":"Ballistik basierend","19":"Psychische Effekte","20":"Nicht Nutzbar in Himmelskämpfen","1__1":"Makes contact","2__1":"Has a charging turn","3__1":"Must recharge","4__1":"Blocked by Detect and Protect","5__1":"Reflectable","6__1":"Snatchable","7__1":"Copied by Mirror Move","8__1":"Punch-based","9__1":"Sound-based","10__1":"Unusable during Gravity","11__1":"Defrosts when used","12__1":"Targets opposite side in triples","13__1":"Heals","14__1":"Ignores Substitute","15__1":"Powder-based","16__1":"Jaw-based","17__1":"Pulse-based","18__1":"Ballistics-based","19__1":"Mental effects","20__1":"Unusable during Sky Battles","4__2":"Blokované Detectem a Protectem","11__2":"Rozmrazí při použití","5__2":"Odrazitelný","10__2":"Nepoužitelný s Gravitací","3__2":"Má dobíjecí kolo","6__2":"Ukradnutelný","8__2":"Úderový","2__2":"Má nabíjecí kolo","9__2":"Zvukový","7__2":"Kopírovatelný Mirror Movem","1__2":"Způsobí dotek","13__2":"Léčí"},"description":{"1":"Der Anwender berührt das Ziel.  Dies löst mahcne Fähigkeiten aus (z.B. []{ability:static}) und Gegenstände (z.B. []{item:sticky-barb}).","2":"Diese Fähigkeit hat eine Aufladerunde, welche mit einer []{item:power-herb} übersprungen werden kann.","3":"Die Runde nach dieser Fähigkeit wird benötigt, damit das Pokémon sich aufladen kann.","4":"Diese Fähigkeit funktioniert nicht, wenn das Ziel []{move:detect} oder []{move:protect} diese Runde genutzt hat.","5":"Diese Fähigkeit könnte reflektiert mit []{move:magic-coat} oder []{ability:magic-bounce} reflektiert werden.","6":"Diese Fähigkeit kann übernommen werden, wenn ein anderes Pokémon []{move:snatch} diese Runde nutzt.","7":"Ein von dieser Fähigkeit getroffenes Pokémon kann []{move:mirror-move} nutzen um diese Fähigkeit zu kopieren.","8":"Diese Fähigkeit hat die 1.2× Kraft, wenn es von einem Pokémon mit []{ability:iron-fist} genutzt wird.","9":"Pokémon mit []{ability:soundproof} sind immun gegen diese Fähigkeit.","10":"Diese Fähigkeit kann nicht bei hoher []{move:gravity} genutzt werden.","11":"Diese Fähigkeit kann genutzt werden, wenn das Pokémon vereist ist um es zu enteisen.","12":"In 3er Kämpfen trifft diese Fähigkeit den entferntesten Gegner.","13":"Diese Fähigkeit wird von []{move:heal-block} blockiert.","14":"Diese Fähigkeit ignoriert den []{move:substitute} des Ziels.","15":"Pokémon mit []{ability:overcoat} und []{type:grass}-Pokémon sind immun gegen diese Fähigkeit.","16":"Diese Fähigkeit hat die 1.5× Kraft, wenn sie von einem Pokémon mit []{ability:strong-jaw} genutzt wird.","17":"Diese Fähigkeit hat die 1.5× Kraft, wenn sie von einem Pokémon mit []{ability:mega-launcher} genutzt wird.","18":"Diese Fähigkeit wird von []{ability:bulletproof} blockiert.","19":"Diese Fähigkeit wird durch []{ability:aroma-veil} blockiert und wird durch []{item:mental-herb} geheilt.","20":"Diese Fähigkeit ist in Himmelskämpfen nicht nutzbar.","1__1":"User touches the target.  This triggers some abilities (e.g., []{ability:static}) and items (e.g., []{item:sticky-barb}).","2__1":"This move has a charging turn that can be skipped with a []{item:power-herb}.","3__1":"The turn after this move is used, the Pokémon's action is skipped so it can recharge.","4__1":"This move will not work if the target has used []{move:detect} or []{move:protect} this turn.","5__1":"This move may be reflected back at the user with []{move:magic-coat} or []{ability:magic-bounce}.","6__1":"This move will be stolen if another Pokémon has used []{move:snatch} this turn.","7__1":"A Pokémon targeted by this move can use []{move:mirror-move} to copy it.","8__1":"This move has 1.2× its usual power when used by a Pokémon with []{ability:iron-fist}.","9__1":"Pokémon with []{ability:soundproof} are immune to this move.","10__1":"This move cannot be used in high []{move:gravity}.","11__1":"This move can be used while frozen to force the Pokémon to defrost.","12__1":"In triple battles, this move can be used on either side to target the farthest away opposing Pokémon.","13__1":"This move is blocked by []{move:heal-block}.","14__1":"This move ignores the target's []{move:substitute}.","15__1":"Pokémon with []{ability:overcoat} and []{type:grass}-type Pokémon are immune to this move.","16__1":"This move has 1.5× its usual power when used by a Pokémon with []{ability:strong-jaw}.","17__1":"This move has 1.5× its usual power when used by a Pokémon with []{ability:mega-launcher}.","18__1":"This move is blocked by []{ability:bulletproof}.","19__1":"This move is blocked by []{ability:aroma-veil} and cured by []{item:mental-herb}.","20__1":"This move is unusable during Sky Battles.","4__2":"Tento útok nebude fungovat, použil-li cíl toto kolo []{move:detect} či [protect]{move:protect}.","11__2":"Tento útok může zmražený pokémon použít k rozmrznutí.","5__2":"","10__2":"Tento útok nelze použít při [zvýšené gravitaci]{move:gravity}","3__2":"Kolo po použití tohoto útoku přeskočí Pokémon svůj tah, aby se mohl dobít.","6__2":"Tento útok bude ukraden, pokud jiný Pokémon toto kolo použil []{move:snatch}","8__2":"","2__2":"Tento útok má nabíjecí kolo, které lze přeskočit pomocí []{item:power-herb}.","9__2":"Pokémoni s []{ability:soundproof} jsou proti tomuto útoku odolní.","7__2":"Pokémon co je cílem tohoto útoku ho může zkopírovat pomocí []{move:mirror-move}","1__2":"Uživatel se dotkne cíle.  Toto zaktivuje některé schopnosti (např. []{ability:static}) a věci (např. []{item:sticky-barb}).","13__2":"Tento útok bude blokován pomocí []{move:heal-block}."}}